pycad/__init__.py
pycad/cli.py
pycad/converters/__init__.py
pycad/converters/dicom_to_nifti.py
pycad/converters/dicom_to_nrrd.py
pycad/converters/nifti_to_dicom.py
pycad/converters/nifti_to_nrrd.py
pycad/converters/nifti_to_png.py
pycad/converters/nifti_to_stl.py
pycad/converters/nrrd_to_dicom.py
pycad/converters/nrrd_to_nifti.py
pycad/datasets/__init__.py
pycad/datasets/data_splitter.py
pycad/datasets/monai_dataset_json.py
pycad/datasets/nifti_merger.py
pycad/datasets/png_to_txt_mc.py
pycad/datasets/png_to_txt_ml.py
pycad/datasets/yolo_dataset_yaml.py
pycad/datasets/segmentation/__init__.py
pycad/datasets/segmentation/TotalSegmentator/0_template.py
pycad/datasets/segmentation/TotalSegmentator/__init__.py
pycad/datasets/segmentation/TotalSegmentator/adrenal_gland_left_dataset.py
pycad/datasets/segmentation/TotalSegmentator/adrenal_gland_right_dataset.py
pycad/datasets/segmentation/TotalSegmentator/aorta_dataset.py
pycad/datasets/segmentation/TotalSegmentator/atrial_appendage_left_dataset.py
pycad/datasets/segmentation/TotalSegmentator/autochthon_left_dataset.py
pycad/datasets/segmentation/TotalSegmentator/autochthon_right_dataset.py
pycad/datasets/segmentation/TotalSegmentator/brachiocephalic_trunk_dataset.py
pycad/datasets/segmentation/TotalSegmentator/brachiocephalic_vein_left_dataset.py
pycad/datasets/segmentation/TotalSegmentator/brachiocephalic_vein_right_dataset.py
pycad/datasets/segmentation/TotalSegmentator/brain_dataset.py
pycad/datasets/segmentation/TotalSegmentator/clavicula_left_dataset.py
pycad/datasets/segmentation/TotalSegmentator/clavicula_right.py
pycad/datasets/segmentation/TotalSegmentator/colon_dataset.py
pycad/datasets/segmentation/TotalSegmentator/common_carotid_artery_left_dataset.py
pycad/datasets/segmentation/TotalSegmentator/common_carotid_artery_right_dataset.py
pycad/datasets/segmentation/TotalSegmentator/costal_cartilages_dataset.py
pycad/datasets/segmentation/TotalSegmentator/duodenum_dataset.py
pycad_medic-0.0.10.dist-info/LICENSE
pycad_medic-0.0.10.dist-info/METADATA
pycad_medic-0.0.10.dist-info/WHEEL
pycad_medic-0.0.10.dist-info/entry_points.txt
pycad_medic-0.0.10.dist-info/top_level.txt
pycad_medic-0.0.10.dist-info/RECORD
