Metadata-Version: 2.1
Name: pycad-medic
Version: 0.0.10
Summary: A medical imaging library for Python
Home-page: https://pycad.co
Author: Mohammed El Amine Mokhtari
Author-email: mohammed@pycad.co
Project-URL: Documentation, https://pycad.co
Project-URL: Source Code, https://github.com/amine0110/pycad
License-File: LICENSE
Requires-Dist: numpy ==1.26.0
Requires-Dist: tqdm ==4.66.1
Requires-Dist: glob2
Requires-Dist: SimpleITK ==2.3.0
Requires-Dist: pillow ==10.0.1
Requires-Dist: pydicom ==2.4.3
Requires-Dist: vtk ==9.2.6
Requires-Dist: vedo ==2023.4.6
Requires-Dist: scikit-image ==0.22.0
Requires-Dist: opencv-python ==4.8.1.78
Requires-Dist: pytest-shutil
Requires-Dist: nibabel ==3.2.2
Requires-Dist: gdown ==4.7.1
